<?xml version="1.0" encoding="UTF-8"?>
<CustomerData>
  <GeneralInfo>
    <CSCEdition>ED0007</CSCEdition>
    <Country>Ireland</Country>
    <CountryISO>IE</CountryISO>
    <Region>EUR</Region>
    <SalesCode>MET</SalesCode>
    <NbNetworkInfo>1</NbNetworkInfo>
    <NetworkInfo>
      <MCCMNC>27203</MCCMNC>
      <NetworkName>Meteor</NetworkName>
    </NetworkInfo>
  </GeneralInfo>
  <Settings>
    <Main>
      <Security>
        <OneSIMLock>none</OneSIMLock>
        <NbNetworkLock>1</NbNetworkLock>
        <NetworkLock>27203</NetworkLock>
      </Security>
      <Network>
        <NbFastDormancy>1</NbFastDormancy>
        <FastDormancy>
          <NetworkName>Meteor</NetworkName>
          <FastDormancyEnableStatus>off</FastDormancyEnableStatus>
        </FastDormancy>
        <NbWbAmr>1</NbWbAmr>
        <WbAmr>
          <NetworkName>default</NetworkName>
          <WbAmrCodec>on</WbAmrCodec>
        </WbAmr>
        <AutoProfile>off</AutoProfile>
      </Network>
      <Sound>
        <RngToneAlertType>melody</RngToneAlertType>
        <RngVolume>7</RngVolume>
        <KeyTone>
          <KeyVolume>0</KeyVolume>
        </KeyTone>
        <MsgToneAlertType>melody</MsgToneAlertType>
        <TouchTone>off</TouchTone>
        <ExtraSound>
          <ConnectTone>on</ConnectTone>
          <CallEndTone>off</CallEndTone>
        </ExtraSound>
      </Sound>
      <Phone>
        <AlertOnCall>on</AlertOnCall>
        <DefLanguage>en_IE</DefLanguage>
        <DefLanguageNoSIM>en_IE</DefLanguageNoSIM>
        <T9Enabling>disable</T9Enabling>
        <T9Language>english</T9Language>
        <DateTimeFormat>
          <TimeFormat>12h</TimeFormat>
          <TimezoneUpdate>on</TimezoneUpdate>
        </DateTimeFormat>
        <SmartStay>on</SmartStay>
        <Motion>
          <DirectCall>on</DirectCall>
          <SmartAlert>on</SmartAlert>
        </Motion>
      </Phone>
    </Main>
    <Messages>
      <NbVoicemail>1</NbVoicemail>
      <Voicemail>
        <NetworkName>Meteor</NetworkName>
        <VoicemailName>Voicemail</VoicemailName>
        <TelNum>171</TelNum>
      </Voicemail>
      <SMS>
        <DeliveryReport>off</DeliveryReport>
        <CharSupport>gsmalpha</CharSupport>
        <PreviewMessageNoti>on</PreviewMessageNoti>
      </SMS>
      <MMS>
        <MmsSending>
          <ReqDeliveryRep>off</ReqDeliveryRep>
          <ReqReadRep>off</ReqReadRep>
          <MessageSize>300</MessageSize>
          <CreationMode>free</CreationMode>
        </MmsSending>
        <MmsReceiving>
          <Home>auto</Home>
          <Roaming>manual</Roaming>
        </MmsReceiving>
        <NbMMSView>1</NbMMSView>
        <MMSView>
          <MessageUserAgent>SAMSUNG-ANDROID-MMS/uaprof</MessageUserAgent>
          <MessageUaProfUrl>http://wap.samsungmobile.com/uaprof/uaprof.rdf</MessageUaProfUrl>
        </MMSView>
      </MMS>
      <Email>
        <NbAccount>3</NbAccount>
        <Account>
          <NetworkName>Meteor</NetworkName>
          <AccountName>Google</AccountName>
          <EmailAddr>@gmail.com</EmailAddr>
        </Account>
        <Account>
          <NetworkName>Meteor</NetworkName>
          <AccountName>Yahoo!</AccountName>
          <EmailAddr>@yahoo.com</EmailAddr>
        </Account>
        <Account>
          <NetworkName>Meteor</NetworkName>
          <AccountName>Windows Live</AccountName>
          <EmailAddr>@hotmail.com</EmailAddr>
        </Account>
      </Email>
    </Messages>
    <NbFOTA>1</NbFOTA>
    <FOTA>
      <NetworkName>Meteor</NetworkName>
    </FOTA>
    <Browser>
      <NbBookmark>1</NbBookmark>
      <Bookmark>
        <NetworkName>Meteor</NetworkName>
        <BookmarkName>Yahoo!</BookmarkName>
        <URL>https://yahoo.com/?.tsrc=samsungbm</URL>
      </Bookmark>
      <eManual>
        <URL>http://www.samsung.com/m-manual/common</URL>
      </eManual>
    </Browser>
    <NbWifiProfile>1</NbWifiProfile>
    <WifiProfile>
      <NetworkName>Meteor</NetworkName>
    </WifiProfile>
    <Connections>
      <NbProfileHandle>1</NbProfileHandle>
      <ProfileHandle>
        <NbNetProfile>2</NbNetProfile>
        <NetworkName>Meteor</NetworkName>
        <ProfBrowser>Meteor Data</ProfBrowser>
        <ProfMMS>Meteor MMS</ProfMMS>
        <ProfEmail>Meteor Data</ProfEmail>
      </ProfileHandle>
      <NbProfile>2</NbProfile>
      <Profile>
        <NetworkName>Meteor</NetworkName>
        <Editable>yes</Editable>
        <ProfileName>Meteor MMS</ProfileName>
        <URL>http://mms.mymeteor.ie</URL>
        <Auth>normal</Auth>
        <Protocol>http</Protocol>
        <MTUSize>1500</MTUSize>
        <Proxy>
          <EnableFlag>on</EnableFlag>
          <ServAddr>010.085.085.085</ServAddr>
          <Port>8799</Port>
        </Proxy>
        <PSparam>
          <APN>mms.mymeteor.ie</APN>
          <UserId>my</UserId>
          <Password>wap</Password>
        </PSparam>
      </Profile>
      <Profile>
        <NetworkName>Meteor</NetworkName>
        <Editable>yes</Editable>
        <ProfileName>Meteor Data</ProfileName>
        <URL>http://www.google.ie</URL>
        <Auth>normal</Auth>
        <Protocol>http</Protocol>
        <MTUSize>1500</MTUSize>
        <Proxy>
          <EnableFlag>off</EnableFlag>
        </Proxy>
        <PSparam>
          <APN>data.mymeteor.ie</APN>
        </PSparam>
      </Profile>
    </Connections>
  </Settings>
</CustomerData>